{
  "what_this_is": "SELF-AUTHORED correctness harness for the router \u2014 NOT an agent evaluation. Establishes branch correctness + a soundness regression, not real-world efficacy (see module docstring).",
  "cases": 6,
  "faithful": 3,
  "botched": 3,
  "botches_refused": 3,
  "botches_missed_SILENT_CORRUPTION": 0,
  "faithful_certified": 3,
  "faithful_false_refused": 0,
  "partial_oracle_exploit_fail_closed": true,
  "audit_collapse_note": "collapse% = 1 - |cone|/total is a property of the workbook+edit, NOT the tool; it scales with untouched row count and CRATERS to ~0% on shared-upstream edits (the financial-model case). Reported only for the value-fill cases, pure-rename (tautological 100%) excluded.",
  "collapse_pct_value_fill_cases": [
    84,
    83
  ],
  "per_case": [
    {
      "edit": "faithful_rename",
      "faithful": true,
      "verdict": "CERTIFIED",
      "collapse_pct": 100
    },
    {
      "edit": "faithful_mixed",
      "faithful": true,
      "verdict": "CERTIFIED",
      "collapse_pct": 84
    },
    {
      "edit": "faithful_reorder",
      "faithful": true,
      "verdict": "CERTIFIED",
      "collapse_pct": 83
    },
    {
      "edit": "botch_wrong_op",
      "faithful": false,
      "verdict": "REFUSED",
      "collapse_pct": null
    },
    {
      "edit": "botch_dropped_dep",
      "faithful": false,
      "verdict": "REFUSED",
      "collapse_pct": null
    },
    {
      "edit": "botch_undeclared_fill",
      "faithful": false,
      "verdict": "REFUSED",
      "collapse_pct": null
    }
  ]
}